MANIFEST.in
README.txt
setup.cfg
setup.py
collective/__init__.py
collective.collage.megamenu.egg-info/PKG-INFO
collective.collage.megamenu.egg-info/SOURCES.txt
collective.collage.megamenu.egg-info/dependency_links.txt
collective.collage.megamenu.egg-info/entry_points.txt
collective.collage.megamenu.egg-info/namespace_packages.txt
collective.collage.megamenu.egg-info/not-zip-safe
collective.collage.megamenu.egg-info/requires.txt
collective.collage.megamenu.egg-info/top_level.txt
collective/collage/__init__.py
collective/collage/megamenu/__init__.py
collective/collage/megamenu/atfolder.zcml
collective/collage/megamenu/configure.zcml
collective/collage/megamenu/interfaces.py
collective/collage/megamenu/patch.py
collective/collage/megamenu/ploneappfolder.zcml
collective/collage/megamenu/profiles.zcml
collective/collage/megamenu/rebuild_i18n.sh
collective/collage/megamenu/setuphandlers.py
collective/collage/megamenu/version.txt
collective/collage/megamenu/vocabulary.py
collective/collage/megamenu/browser/__init__.py
collective/collage/megamenu/browser/collage.py
collective/collage/megamenu/browser/collage.zcml
collective/collage/megamenu/browser/configure.zcml
collective/collage/megamenu/browser/controlpanel.py
collective/collage/megamenu/browser/interfaces.py
collective/collage/megamenu/browser/renderer.py
collective/collage/megamenu/browser/viewlet.py
collective/collage/megamenu/browser/views.py
collective/collage/megamenu/browser/resources/collage-patch.js
collective/collage/megamenu/browser/resources/jquery.hoverIntent.minified.js
collective/collage/megamenu/browser/resources/megamenu-classic.css
collective/collage/megamenu/browser/resources/megamenu.css
collective/collage/megamenu/browser/resources/megamenu.gif
collective/collage/megamenu/browser/resources/megamenu.js
collective/collage/megamenu/browser/templates/collage_renderer.pt
collective/collage/megamenu/browser/templates/column_renderer.pt
collective/collage/megamenu/browser/templates/controlpanel.pt
collective/collage/megamenu/browser/templates/menu_column.pt
collective/collage/megamenu/browser/templates/menu_content.pt
collective/collage/megamenu/browser/templates/menu_item.pt
collective/collage/megamenu/browser/templates/menu_renderer.pt
collective/collage/megamenu/browser/templates/menu_row.pt
collective/collage/megamenu/browser/templates/nested_collage.pt
