Metadata-Version: 1.0
Name: collective.collage.megamenu
Version: 1.1.2
Summary: A mega drop down menu implementation using Products.Collage
Home-page: http://svn.plone.org/svn/collective/Products.Collage/addons/collective.collage.megamenu
Author: Marcos F. Romero
Author-email: marcos.romero {at} inter-cultura {dot} com
License: GPL
Platform: UNKNOWN
Classifier: Framework :: Plone
Classifier: Programming Language :: Python
